greenflow_dask_plugin/__init__.py
greenflow_dask_plugin/daskComputeNode.py
greenflow_dask_plugin/persistNode.py
greenflow_dask_plugin/simpleParallelNode.py
greenflow_dask_plugin-0.0.1.dist-info/METADATA
greenflow_dask_plugin-0.0.1.dist-info/WHEEL
greenflow_dask_plugin-0.0.1.dist-info/entry_points.txt
greenflow_dask_plugin-0.0.1.dist-info/top_level.txt
greenflow_dask_plugin-0.0.1.dist-info/RECORD
